mydia/__init__.py
mydia/mydia.py
mydia/utils.py
mydia-2.2.1.dist-info/LICENSE
mydia-2.2.1.dist-info/METADATA
mydia-2.2.1.dist-info/WHEEL
mydia-2.2.1.dist-info/top_level.txt
mydia-2.2.1.dist-info/RECORD
