Metadata-Version: 2.1
Name: mydia
Version: 2.2.1
Summary: A simple and efficient wrapper for reading videos as NumPy tensors.
Home-page: https://github.com/MrinalJain17/mydia
Author: Mrinal Jain
Author-email: mrinaljain007@gmail.com
License: MIT
Project-URL: Documentation, https://mrinaljain17.github.io/mydia/
Project-URL: Source, https://github.com/MrinalJain17/mydia
Platform: UNKNOWN
Classifier: Development Status :: 3 - Alpha
Classifier: Intended Audience :: Developers
Classifier: Intended Audience :: Education
Classifier: Intended Audience :: Science/Research
Classifier: License :: OSI Approved :: MIT License
Classifier: Programming Language :: Python :: 3
Classifier: Programming Language :: Python :: 3.6
Classifier: Topic :: Software Development :: Libraries :: Python Modules
Classifier: Topic :: Multimedia :: Video :: Capture
Requires-Dist: numpy (>=1.14.5)
Requires-Dist: ffmpeg-python (>=0.1.16)
Requires-Dist: tqdm (>=4.25.0)
